LICENSE
MANIFEST.in
README.rst
setup.py
django_writeback.egg-info/PKG-INFO
django_writeback.egg-info/SOURCES.txt
django_writeback.egg-info/dependency_links.txt
django_writeback.egg-info/requires.txt
django_writeback.egg-info/top_level.txt
writeback/__init__.py
writeback/admin.py
writeback/context.py
writeback/forms.py
writeback/models.py
writeback/settings.py
writeback/tests.py
writeback/urls.py
writeback/views.py
writeback/locale/ru/LC_MESSAGES/django.mo
writeback/locale/ru/LC_MESSAGES/django.po
writeback/static/writeback/css/writeback.css
writeback/static/writeback/img/ajax-loader.gif
writeback/static/writeback/js/jquery.min.1.11.1.js
writeback/static/writeback/js/writeback.js
writeback/templates/writeback/button.html
writeback/templates/writeback/email_notification.html
writeback/templates/writeback/header.html