Metadata-Version: 1.1
Name: django-writeback
Version: 0.3.8
Summary: A pluggable customizable Django app to collect feedback from site visitors.
Home-page: https://github.com/timgin/django-writeback/
Author: Timour Ghinatoulline
Author-email: tim@plusone.su
License: BSD License
Keywords: blog,django,feedback,ajax,user,customer,comment
Platform: UNKNOWN
Classifier: Environment :: Web Environment
Classifier: Framework :: Django
Classifier: Intended Audience :: Developers
Classifier: License :: OSI Approved :: BSD License
Classifier: Operating System :: OS Independent
Classifier: Programming Language :: Python
Classifier: Programming Language :: Python :: 2.6
Classifier: Programming Language :: Python :: 2.7
Classifier: Topic :: Internet :: WWW/HTTP
Classifier: Topic :: Internet :: WWW/HTTP :: Dynamic Content
